{"is_source_file": true, "format": "Dart", "description": "Defines a Flutter widget called TagChip for selecting/filtering tags in the UI.", "external_files": ["package:flutter/material.dart", "../models/tag.dart"], "external_methods": ["Theme.of", "ColorScheme.primary", "Colors.grey", "TextStyle", "ChoiceChip", "Padding", "Text"], "published": ["TagChip"], "classes": [{"name": "TagChip", "description": "A stateless widget that displays a choice chip representing a tag, with visual states for active/inactive."}], "methods": [{"name": "TagChip", "description": "Constructor for creating a TagChip widget, with optional tag, required isActive, and optional onTap callback.", "parameters": {"key": "super.key", "tag": "An optional Tag object", "isActive": "Boolean indicating if the chip is active", "onTap": "Optional tap callback"}}, {"name": "build", "description": "Builds the widget tree for TagChip, displaying a ChoiceChip with label and styling based on its state."}], "calls": ["Theme.of(context)", "Theme.of(context).colorScheme.primary", "Colors.grey.withOpacity", "Theme.of(context).colorScheme.primary", "onTap?.call()"], "search-terms": ["TagChip", "Flutter ChoiceChip", "tag filtering", "widget", "stateless widget"], "state": 2, "file_id": 25, "knowledge_revision": 53, "git_revision": "", "hash": "4223e75c4a3a8b1342d95f9b34b9c872", "format-version": 4, "code-base-name": "notes_flutter_frontend", "filename": "notes_flutter_frontend/lib/widgets/tag_chip.dart", "revision_history": [{"53": ""}]}